README.txt
setup.cfg
setup.py
collective/__init__.py
collective.portlet.explore.egg-info/PKG-INFO
collective.portlet.explore.egg-info/SOURCES.txt
collective.portlet.explore.egg-info/dependency_links.txt
collective.portlet.explore.egg-info/entry_points.txt
collective.portlet.explore.egg-info/namespace_packages.txt
collective.portlet.explore.egg-info/not-zip-safe
collective.portlet.explore.egg-info/requires.txt
collective.portlet.explore.egg-info/top_level.txt
collective/portlet/__init__.py
collective/portlet/explore/__init__.py
collective/portlet/explore/configure.zcml
collective/portlet/explore/explorerportlet.py
collective/portlet/explore/recurse.pt
collective/portlet/explore/version.txt
collective/portlet/explore/browser/__init__.py
collective/portlet/explore/browser/configure.zcml
collective/portlet/explore/browser/expand.py
collective/portlet/explore/locales/collective.portlet.explore.pot
collective/portlet/explore/locales/fr/LC_MESSAGES/collective.portlet.explore.mo
collective/portlet/explore/locales/fr/LC_MESSAGES/collective.portlet.explore.po
collective/portlet/explore/locales/nl/LC_MESSAGES/collective.portlet.explore.mo
collective/portlet/explore/locales/nl/LC_MESSAGES/collective.portlet.explore.po
collective/portlet/explore/profiles/default/cssregistry.xml
collective/portlet/explore/profiles/default/jsregistry.xml
collective/portlet/explore/profiles/default/metadata.xml
collective/portlet/explore/profiles/default/portlets.xml
collective/portlet/explore/profiles/default/skins.xml
collective/portlet/explore/skins/explorer/explorer.css.dtml
collective/portlet/explore/skins/explorer/explorer.js
collective/portlet/explore/skins/explorer/tinyspinner.gif
collective/portlet/explore/skins/explorer/tinyspinner.gif.metadata
collective/portlet/explore/skins/explorer/twistie-closed-gray.gif
collective/portlet/explore/skins/explorer/twistie-closed-gray.gif.metadata
collective/portlet/explore/skins/explorer/twistie-closed-over.gif
collective/portlet/explore/skins/explorer/twistie-closed-over.gif.metadata
collective/portlet/explore/skins/explorer/twistie-closed.gif
collective/portlet/explore/skins/explorer/twistie-closed.gif.metadata
collective/portlet/explore/skins/explorer/twistie-open-gray.gif
collective/portlet/explore/skins/explorer/twistie-open-gray.gif.metadata
collective/portlet/explore/skins/explorer/twistie-open-over.gif
