Metadata-Version: 1.1
Name: collective.portlet.explore
Version: 1.2
Summary: A navigation portlet
Home-page: http://www.jarn.com
Author: Jarn
Author-email: plone-developers@lists.sourceforge.net
License: GPL
Platform: UNKNOWN
Classifier: Framework :: Plone
Classifier: Programming Language :: Python
Classifier: Topic :: Software Development :: Libraries :: Python Modules
